blitskrieg_proto/__init__.py
blitskrieg_proto/blitskrieg_pb2.py
blitskrieg_proto/blitskrieg_pb2_grpc.py
blitskrieg_proto-0.2.0.dist-info/WHEEL
blitskrieg_proto-0.2.0.dist-info/METADATA
blitskrieg_proto-0.2.0.dist-info/RECORD
