Metadata-Version: 2.1
Name: blitskrieg-proto
Version: 0.2.0
Summary: Protobuf generated libraries for Blitskrieg
Home-page: https://gitlab.com/hashbeam/blitskrieg-proto
License:  AGPL-3.0-or-later
Keywords: blitskrieg,protobuf,grpc,lightning network,bitcoin
Author: Hashbeam
Author-email: hashbeam@protonmail.com
Requires-Python: >=3.7.0,<4.0.0
Classifier: Development Status :: 4 - Beta
Classifier: Intended Audience :: Developers
Classifier: License :: Other/Proprietary License
Classifier: Natural Language :: English
Classifier: Operating System :: MacOS
Classifier: Operating System :: POSIX :: Linux
Classifier: Programming Language :: Python :: 3
Classifier: Programming Language :: Python :: 3.10
Classifier: Programming Language :: Python :: 3.7
Classifier: Programming Language :: Python :: 3.8
Classifier: Programming Language :: Python :: 3.9
Classifier: Topic :: Other/Nonlisted Topic
Requires-Dist: grpcio (>=1.43.0,<2.0.0)
Requires-Dist: protobuf (>=3.19.1,<4.0.0)
Project-URL: Repository, https://gitlab.com/hashbeam/blitskrieg-proto
